odoo8_addon_l10n_it_codici_carica-8.0.1.0.0-py2.7-nspkg.pth
odoo8_addon_l10n_it_codici_carica-8.0.1.0.0.dist-info/DESCRIPTION.rst
odoo8_addon_l10n_it_codici_carica-8.0.1.0.0.dist-info/METADATA
odoo8_addon_l10n_it_codici_carica-8.0.1.0.0.dist-info/RECORD
odoo8_addon_l10n_it_codici_carica-8.0.1.0.0.dist-info/WHEEL
odoo8_addon_l10n_it_codici_carica-8.0.1.0.0.dist-info/metadata.json
odoo8_addon_l10n_it_codici_carica-8.0.1.0.0.dist-info/namespace_packages.txt
odoo8_addon_l10n_it_codici_carica-8.0.1.0.0.dist-info/top_level.txt
odoo_addons/l10n_it_codici_carica/README.rst
odoo_addons/l10n_it_codici_carica/__init__.py
odoo_addons/l10n_it_codici_carica/__openerp__.py
odoo_addons/l10n_it_codici_carica/data/codici_carica_data.xml
odoo_addons/l10n_it_codici_carica/i18n/it.po
odoo_addons/l10n_it_codici_carica/models/__init__.py
odoo_addons/l10n_it_codici_carica/models/codice_carica.py
odoo_addons/l10n_it_codici_carica/security/ir.model.access.csv
odoo_addons/l10n_it_codici_carica/views/codice_carica_view.xml
